explorium_mcp_server/__init__.py
explorium_mcp_server/__main__.py
explorium_mcp_server/_shared.py
explorium_mcp_server/tools_businesses.py
explorium_mcp_server/tools_prospects.py
explorium_mcp_server/models/__init__.py
explorium_mcp_server/models/_shared.py
explorium_mcp_server/models/businesses.py
explorium_mcp_server/models/prospects.py
pipeiq_explorium_mcp_server-0.1.5.dist-info/METADATA
pipeiq_explorium_mcp_server-0.1.5.dist-info/WHEEL
pipeiq_explorium_mcp_server-0.1.5.dist-info/entry_points.txt
pipeiq_explorium_mcp_server-0.1.5.dist-info/licenses/LICENSE.md
pipeiq_explorium_mcp_server-0.1.5.dist-info/RECORD
